_pymeshview.cpython-38-x86_64-linux-gnu.so
pymeshview/utils.py
pymeshview/__init__.py
pymeshview/examples/show_mesh.py
pymeshview/examples/__init__.py
pymeshview-0.0.4.dist-info/METADATA
pymeshview-0.0.4.dist-info/top_level.txt
pymeshview-0.0.4.dist-info/RECORD
pymeshview-0.0.4.dist-info/entry_points.txt
pymeshview-0.0.4.dist-info/WHEEL
pymeshview-0.0.4.dist-info/LICENSE.md
